abstract_utilities/__init__.py
abstract_utilities/abstract_classes.py
abstract_utilities/circular_import_finder.py
abstract_utilities/circular_import_finder2.py
abstract_utilities/class_utils.py
abstract_utilities/collator_utils.py
abstract_utilities/doit.py
abstract_utilities/dynimport.py
abstract_utilities/error_utils.py
abstract_utilities/global_utils.py
abstract_utilities/hash_utils.py
abstract_utilities/history_utils.py
abstract_utilities/imports.py
abstract_utilities/json_utils.py
abstract_utilities/list_utils.py
abstract_utilities/log_utils.py
abstract_utilities/math_utils.py
abstract_utilities/parse_utils.py
abstract_utilities/path_utils.py
abstract_utilities/read_write_utils.py
abstract_utilities/safe_utils.py
abstract_utilities/string_clean.py
abstract_utilities/string_utils.py
abstract_utilities/tetsts.py
abstract_utilities/thread_utils.py
abstract_utilities/time_utils.py
abstract_utilities/type_utils.py
abstract_utilities/utils.py
abstract_utilities/class_utils/__init__.py
abstract_utilities/class_utils/abstract_classes.py
abstract_utilities/class_utils/caller_utils.py
abstract_utilities/class_utils/class_utils.py
abstract_utilities/class_utils/function_utils.py
abstract_utilities/class_utils/global_utils.py
abstract_utilities/class_utils/module_utils.py
abstract_utilities/class_utils/imports/__init__.py
abstract_utilities/class_utils/imports/imports.py
abstract_utilities/class_utils/imports/utils.py
abstract_utilities/cmd_utils/__init__.py
abstract_utilities/cmd_utils/cmd_utils.py
abstract_utilities/cmd_utils/pexpect_utils.py
abstract_utilities/cmd_utils/user_utils.py
abstract_utilities/cmd_utils/imports/__init__.py
abstract_utilities/cmd_utils/imports/imports.py
abstract_utilities/compare_utils/__init__.py
abstract_utilities/compare_utils/best_match.py
abstract_utilities/compare_utils/compare_utils.py
abstract_utilities/compare_utils/find_value.py
abstract_utilities/directory_utils/__init__.py
abstract_utilities/directory_utils/directory_utils.py
abstract_utilities-0.2.2.715.dist-info/METADATA
abstract_utilities-0.2.2.715.dist-info/WHEEL
abstract_utilities-0.2.2.715.dist-info/top_level.txt
abstract_utilities-0.2.2.715.dist-info/RECORD
