Metadata-Version: 2.4
Name: abstract_utilities
Version: 0.2.2.715
Summary: abstract_utilities is a collection of utility modules providing a variety of functions to aid in tasks such as data comparison, list manipulation, JSON handling, string manipulation, mathematical computations, and time operations.
Home-page: https://github.com/AbstractEndeavors/abstract_utilities
Author: putkoff
Author-email: partners@abstractendeavors.com
Classifier: Development Status :: 3 - Alpha
Classifier: Intended Audience :: Developers
Classifier: License :: OSI Approved :: MIT License
Classifier: Programming Language :: Python :: 3
Classifier: Programming Language :: Python :: 3.11
Requires-Python: >=3.11
Requires-Dist: pathlib>=1.0.1
Requires-Dist: abstract_security>=0.0.1
Requires-Dist: yt_dlp>=2023.10.13
Requires-Dist: pexpect>=4.8.0
Dynamic: author
Dynamic: author-email
Dynamic: classifier
Dynamic: description
Dynamic: description-content-type
Dynamic: home-page
Dynamic: requires-dist
Dynamic: requires-python
Dynamic: summary
